{
  "dashboards": [
    {
      "id": "south-media-dashboard",
      "name": "South Media Dashboard",
      "description": "Dashboard principal com dados de canais e footfall",
      "url": "https://dash.iasouth.tech/static/dash_sonho.html",
      "thumbnail": "📊",
      "services": {
        "channels": {
          "name": "Atualização de Canais",
          "endpoint": "https://dashboard-automation-6f3ckz7c7q-uc.a.run.app/trigger",
          "statusEndpoint": "https://dashboard-automation-6f3ckz7c7q-uc.a.run.app/status",
          "description": "Atualiza dados dos canais (YouTube, TikTok, Netflix, etc.)"
        },
        "footfall": {
          "name": "Atualização de Footfall",
          "endpoint": "https://footfall-automation-609095880025.us-central1.run.app/trigger",
          "statusEndpoint": "https://footfall-automation-609095880025.us-central1.run.app/status",
          "description": "Atualiza dados de footfall das lojas físicas"
        }
      },
      "settings": {
        "autoSync": false,
        "syncInterval": 3600000,
        "logRetention": 50
      },
      "metadata": {
        "created": "2025-09-14T12:00:00Z",
        "version": "1.0.0",
        "owner": "South Media IA"
      }
    }
  ],
  "panel": {
    "name": "Painel de Controle South Media IA",
    "version": "1.0.0",
    "autoRefresh": 30000,
    "theme": "gradient",
    "settings": {
      "maxLogs": 20,
      "showTimestamps": true,
      "enableNotifications": true
    }
  }
}
